personalVisualisation/__init__.py
personalVisualisation/popup.py
personalVisualisation/test.py
personalVisualisation/visualise.py
personalVisualisation/images/__init__.py
personalVisualisation/images/bar.py
personalVisualisation/images/line.py
personalVisualisation/images/pie.py
personalVisualisation-1.3.1.dist-info/METADATA
personalVisualisation-1.3.1.dist-info/WHEEL
personalVisualisation-1.3.1.dist-info/entry_points.txt
personalVisualisation-1.3.1.dist-info/top_level.txt
personalVisualisation-1.3.1.dist-info/RECORD
