Metadata-Version: 2.1
Name: personalVisualisation
Version: 1.3.1
Summary: All functions that assist in standardising development approaches.
Home-page: https://github.com/yourusername/your-repo
Author: Marcus
Author-email: marcusongkiansiong@gmail.com
Classifier: Programming Language :: Python :: 3
Classifier: License :: OSI Approved :: MIT License
Classifier: Operating System :: OS Independent
Requires-Python: >=3.6
Requires-Dist: custom-development-standardisation >=1.1.2
Requires-Dist: matplotlib >=3.8.3
Requires-Dist: pandas >=2.2.2
Requires-Dist: Pillow >=10.4.0
